{
  "app": {
    "name": "Uangly",
    "subtitle": "Money Management"
  },
  "navigation": {
    "dashboard": "Dashboard",
    "transactions": "Transactions",
    "goals": "Goals",
    "accounts": "Accounts",
    "balance_analysis": "Balance Analysis",
    "balance": "Balance",
    "ai_advisor": "AI Advisor",
    "settings": "Settings",
    "logout": "Logout"
  },
  "sidebar": {
    "welcome_back": "Welcome back,",
    "total_balance": "Total Balance",
    "secured_encrypted": "Secured & Encrypted",
    "pro_badge": "Pro"
  },
  "quick_transaction": {
    "title": "Quick Add Transaction",
    "subtitle": "Add your transaction in seconds",
    "transaction_type": "Transaction Type",
    "choose_type": "Choose transaction type",
    "income": "💰 Income",
    "expense": "💸 Expense",
    "amount": "Amount",
    "enter_amount": "Enter amount",
    "scope": "Scope",
    "select_scope": "Select scope",
    "wallet": "Wallet",
    "select_wallet": "Select wallet",
    "category": "Category",
    "select_category": "Select category (optional)",
    "description": "Description",
    "description_placeholder": "What is this transaction for?",
    "date_time": "Date & Time",
    "tags": "Tags",
    "tags_placeholder": "food, entertainment, work",
    "note": "Note (Optional)",
    "note_placeholder": "Any additional notes about this transaction...",
    "cancel": "Cancel",
    "save_transaction": "Save Transaction",
    "saving": "Saving...",
    "success_message": "Transaction saved successfully! 🎉",
    "error_message": "Error saving transaction. Please try again.",
    "validation_error": "Please fill in all required fields (Type, Amount, Scope, Wallet)"
  },
  "notifications": {
    "success": "Success",
    "warning": "Warning",
    "error": "Error",
    "info": "Info"
  },
  "footer": {
    "copyright": "© 2025 Uangly. Built with ❤️ by taroleague"
  },
  "language": {
    "select": "Select Language",
    "english": "English",
    "indonesian": "Bahasa Indonesia"
  },
  "dashboard": {
    "welcome_back": "Welcome back,",
    "financial_overview": "Here's your financial overview for",
    "year": "Year:",
    "month": "Month:",
    "day": "Day:",
    "current": "Current",
    "quick_access": "Quick Access",
    "total_balance": "Total Balance",
    "income": "Income",
    "expenses": "Expenses",
    "transactions": "Transactions",
    "monthly_overview": "Monthly Overview",
    "daily_overview": "Daily Overview",
    "yearly_overview": "Yearly Overview",
    "recent_transactions": "Recent Transactions",
    "view_all": "View All",
    "all": "All",
    "top_tags": "Top Tags",
    "no_transactions": "No transactions yet",
    "no_transactions_month": "No transactions for this month",
    "no_tags": "No tags found",
    "start_adding_tags": "Start adding tags to your transactions to see them here",
    "yesterday": "Yesterday",
    "previous_month": "Previous Month",
    "no_change": "No change",
    "unable_to_calculate": "Unable to calculate",
    "no_data": "No data",
    "less": "less",
    "more": "more",
    "quick_actions": "Quick Actions",
    "add_transaction": "Add Transaction",
    "update_balance": "Update Balance",
    "set_goals": "Set Goals",
    "close": "Close",
    "loading_years": "Loading years...",
    "loading_months": "Loading months...",
    "all_months": "All Months",
    "all_days": "All Days",
    "current_year": "Current Year",
    "current_month": "Current Month",
    "today": "Today",
    "days_ago": "days ago"
  },
  "transactions": {
    "title": "Transactions",
    "subtitle": "Manage your financial transactions",
    "transaction_history": "Transaction History",
    "back_to_menu": "Back to Menu",
    "all_wallets": "All Wallets",
    "search_filter": "Search & Filter Transactions",
    "search_placeholder": "Search transactions...",
    "all_types": "All Types",
    "all_categories": "All Categories",
    "date_from": "Date From",
    "date_to": "Date To",
    "min_amount": "Min Amount",
    "max_amount": "Max Amount",
    "apply_filters": "Apply Filters",
    "clear_all": "Clear All",
    "cancel": "Cancel",
    "close": "Close",
    "date": "Date",
    "type": "Type",
    "amount": "Amount",
    "balance_before": "Balance Before",
    "balance_after": "Balance After",
    "category": "Category",
    "actions": "Actions",
    "income": "Income",
    "expense": "Expense",
    "transfer": "Transfer",
    "balance_adjustment": "Balance Adjustment",
    "no_tags": "No tags",
    "view_details": "View Details",
    "edit_transaction": "Edit Transaction",
    "delete_transaction": "Delete Transaction",
    "no_transactions_found": "No transactions found",
    "try_adjusting_filters": "Try adjusting your filters or add a new transaction.",
    "showing": "Showing",
    "to": "to",
    "of": "of",
    "transactions": "transactions",
    "show": "Show:",
    "per_page": "per page",
    "previous": "Previous",
    "next": "Next",
    "edit_transaction_modal": "Edit Transaction",
    "amount_label": "Amount *",
    "amount_placeholder": "1.000.000",
    "amount_help": "Format: 1.000.000 (gunakan titik sebagai separator ribuan)",
    "type_label": "Type *",
    "category_label": "Category",
    "select_category": "Select Category",
    "saving_space": "Saving Space",
    "select_saving_space": "Select Saving Space",
    "scope_label": "Scope",
    "select_scope": "Select Scope",
    "date_time": "Date & Time",
    "tags_label": "Tags (comma separated)",
    "tags_placeholder": "food, entertainment, work",
    "note_label": "Note",
    "update_transaction": "Update Transaction",
    "delete_confirm": "Are you sure you want to delete this transaction?",
    "transaction_updated": "Transaction updated and balances recalculated successfully!",
    "transaction_deleted": "Transaction deleted successfully!",
    "transaction_added": "Transaction added successfully!",
    "failed_update": "Failed to update transaction",
    "failed_delete": "Failed to delete transaction",
    "failed_add": "Failed to add transaction",
    "failed_load": "Failed to load transaction data",
    "updating": "Updating...",
    "recalculating": "Recalculating balances...",
    "transaction_details": "Transaction Details",
    "basic_information": "Basic Information",
    "balance_information": "Balance Information",
    "transfer_details": "Transfer Details",
    "from": "From:",
    "to": "To:",
    "fee": "Fee:",
    "transfer_fee": "Transfer Fee",
    "tags": "Tags",
    "note": "Note",
    "by_system_only": "by system only"
  },
  "transaction_type": {
    "title": "Transactions",
    "subtitle": "Choose what you want to do",
    "add_transaction": "Add Transaction",
    "add_transaction_desc": "Create new income or expense",
    "transaction_history": "Transaction History",
    "transaction_history_desc": "View and filter transactions",
    "transfer": "Transfer",
    "transfer_desc": "Move money between wallets",
    "modified_balance": "Modified Balance",
    "modified_balance_desc": "Adjust wallet balance",
    "quick_tips": "Select an action above to proceed",
    "add_new_transaction": "Add New Transaction",
    "step_1_select_scope": "Step 1: Select Scope",
    "step_2_select_saving_space": "Step 2: Select Saving Space",
    "step_3_transaction_type": "Step 3: Transaction Type",
    "step_4_category_tags": "Step 4: Category & Tags",
    "step_5_transaction_amount": "Step 5: Transaction Amount",
    "step_6_date_confirmation": "Step 6: Date Confirmation",
    "step_7_final_note": "Step 7: Final Note",
    "select_scope": "Select Scope",
    "choose_scope": "Choose the scope for this transaction",
    "select_saving_space": "Select Saving Space",
    "choose_wallet": "Choose which wallet this transaction affects",
    "wallets_disabled_info": "Wallets with 0 balance are disabled.",
    "go_to_balance": "Go to Balance page",
    "to_add_funds": "to add funds.",
    "transaction_type_title": "Transaction Type",
    "is_income_expense": "Is this income or expense?",
    "income": "Income",
    "expense": "Expense",
    "category_tags": "Category & Tags",
    "categorize_tag": "Categorize and tag your transaction",
    "sequence_info": "Sequence number will be automatically assigned based on the latest manual balance",
    "category": "Category",
    "select_category": "Select Category",
    "tags_comma_separated": "Tags (comma separated)",
    "tags_placeholder": "food, entertainment, work",
    "transaction_amount": "Transaction Amount",
    "enter_amount": "Enter the amount for this transaction",
    "available_balance": "Available Balance:",
    "expense_limit": "For expense transactions, amount cannot exceed available balance",
    "insufficient_balance": "Insufficient Balance!",
    "amount_exceeds": "Amount exceeds available balance",
    "amount_format": "Format: 1.000.000 (gunakan titik sebagai separator ribuan)",
    "date_confirmation": "Date Confirmation",
    "transaction_recent": "Just to make sure, this transaction happened recently, right?",
    "yes_recent": "Yes, it's recent",
    "no_pick_date": "No, pick different date",
    "select_date_time": "Select Date & Time",
    "choose_when": "Choose when this transaction occurred",
    "confirm_date": "Confirm Date",
    "final_note": "Final Note",
    "add_notes": "Add any additional notes (optional)",
    "notes_placeholder": "Add any notes about this transaction...",
    "selected_options": "Selected Options:",
    "scope": "Scope:",
    "saving_space": "Saving Space:",
    "type": "Type:",
    "amount": "Amount:",
    "cancel": "Cancel",
    "previous": "Previous",
    "next": "Next",
    "submit_transaction": "Submit Transaction",
    "modified_balance_title": "Modified Balance",
    "adjust_wallet_balance": "Adjust Wallet Balance",
    "set_actual_balance": "Set the actual balance of your wallet. The difference will be recorded as a transaction.",
    "select_saving_space": "Select Saving Space",
    "new_balance_amount": "New Balance Amount",
    "balance_difference": "Balance Difference:",
    "amount_recorded": "This amount will be recorded as a transaction",
    "update_balance": "Update Balance",
    "transfer_money": "Transfer Money",
    "transfer_between_wallets": "Transfer Between Wallets",
    "move_money": "Move money from one wallet to another with optional admin fee.",
    "from_wallet": "From Wallet",
    "select_source_wallet": "Select Source Wallet",
    "to_wallet": "To Wallet",
    "select_destination_wallet": "Select Destination Wallet",
    "transfer_amount": "Transfer Amount",
    "admin_fee_optional": "Admin Fee (Optional)",
    "optional_admin_fee": "Optional admin fee for the transfer",
    "transfer_money_btn": "Transfer Money",
    "please_select_scope": "Please select a scope",
    "please_select_saving_space": "Please select a saving space",
    "wallet_zero_balance": "This wallet has 0 balance. Please go to Balance page to add funds first.",
    "please_select_type": "Please select transaction type",
    "please_enter_amount": "Please enter transaction amount",
    "please_confirm_date": "Please confirm the transaction date first",
    "please_select_date": "Please select a date and time",
    "timestamp_missing": "Timestamp is missing. Please go back and confirm the date.",
    "transaction_added": "Transaction added successfully!",
    "failed_add_transaction": "Failed to add transaction",
    "please_select_saving_space_balance": "Please select a saving space",
    "please_enter_new_balance": "Please enter the new balance amount",
    "balance_same": "The new balance is the same as current balance. No changes needed.",
    "balance_updated": "Balance updated successfully!",
    "failed_update_balance": "Failed to update balance",
    "please_select_source": "Please select source wallet",
    "please_select_destination": "Please select destination wallet",
    "same_wallets": "Source and destination wallets cannot be the same",
    "please_enter_transfer_amount": "Please enter transfer amount",
    "insufficient_balance_transfer": "Insufficient balance. Available: IDR {available}, Required: IDR {required}",
    "transfer_completed": "Transfer completed successfully!",
    "failed_complete_transfer": "Failed to complete transfer"
  },
  "accounts": {
    "title": "My Accounts",
    "subtitle": "Manage and view all accounts & wallets",
    "total_accounts": "Total Accounts",
    "total_balance": "Total Balance",
    "no_accounts_found": "No Accounts Found",
    "no_accounts_desc": "You haven't created any accounts yet. Start by adding your first wallet or bank account.",
    "add_account": "Add Account",
    "tap_to_view_transactions": "Tap to view transactions",
    "quick_actions": "Quick Actions",
    "choose_action": "Choose what you want to do with this account",
    "add_transaction": "Add Transaction",
    "transfer": "Transfer",
    "modified_balance": "Modified Balance",
    "cancel": "Cancel",
    "add_transaction_modal": "Add Transaction",
    "scope_label": "Scope",
    "select_scope": "Select Scope",
    "saving_space_label": "Saving Space",
    "select_saving_space": "Select Saving Space",
    "transaction_type_label": "Transaction Type",
    "select_type": "Select Type",
    "income": "Income",
    "expense": "Expense",
    "category_label": "Category",
    "select_category": "Select Category",
    "by_system_only": "(by system only)",
    "amount_label": "Amount",
    "amount_placeholder": "1.000.000",
    "tags_label": "Tags (comma separated)",
    "tags_placeholder": "food, entertainment, work",
    "note_label": "Note (optional)",
    "note_placeholder": "Add any notes about this transaction...",
    "transfer_money_modal": "Transfer Money",
    "from_wallet": "From Wallet",
    "select_source_wallet": "Select Source Wallet",
    "to_wallet": "To Wallet",
    "select_destination_wallet": "Select Destination Wallet",
    "transfer_amount": "Transfer Amount",
    "admin_fee_optional": "Admin Fee (Optional)",
    "transfer_money_btn": "Transfer Money",
    "modified_balance_modal": "Modified Balance",
    "select_saving_space": "Select Saving Space",
    "new_balance_amount": "New Balance Amount",
    "update_balance": "Update Balance",
    "please_fill_required_fields": "Please fill in all required fields",
    "transaction_added": "Transaction added successfully!",
    "failed_add_transaction": "Failed to add transaction",
    "same_wallets_error": "Source and destination wallets cannot be the same",
    "transfer_completed": "Transfer completed successfully!",
    "failed_complete_transfer": "Failed to complete transfer",
    "balance_same": "The new balance is the same as current balance. No changes needed.",
    "balance_updated": "Balance updated successfully!",
    "failed_update_balance": "Failed to update balance",
    "all_scopes": "All",
    "no_scopes_available": "No scopes available"
  },
  "settings": {
    "title": "Settings",
    "subtitle": "Manage your financial categories, saving spaces, and scopes",
    "scopes": "Scopes",
    "saving_spaces": "Saving Spaces",
    "categories": "Categories",
    "scopes_management": "Scopes Management",
    "add_scope": "Add Scope",
    "no_scopes_created": "No scopes created yet",
    "create_first_scope": "Create your first scope to organize your finances",
    "saving_spaces_management": "Saving Spaces",
    "add_saving_space": "Add Saving Space",
    "no_saving_spaces_created": "No saving spaces created yet",
    "create_first_saving_space": "Create your first saving space to track your money",
    "categories_management": "Categories",
    "add_category": "Add Category",
    "no_categories_created": "No categories created yet",
    "create_first_category": "Create your first category to organize transactions",
    "no_description": "No description",
    "system": "System",
    "edit": "Edit",
    "delete": "Delete",
    "cancel": "Cancel",
    "save": "Save",
    "add_new_scope": "Add New Scope",
    "scope_name": "Scope Name",
    "scope_name_required": "Scope Name *",
    "enter_scope_name": "Enter scope name",
    "description": "Description",
    "enter_description_optional": "Enter scope description (optional)",
    "save_scope": "Save Scope",
    "edit_scope": "Edit Scope",
    "add_new_saving_space": "Add New Saving Space",
    "saving_space_name": "Saving Space Name",
    "saving_space_name_required": "Saving Space Name *",
    "enter_saving_space_name": "Enter saving space name",
    "type": "Type",
    "type_required": "Type *",
    "select_type": "Select type...",
    "bank": "Bank",
    "ewallet": "E-Wallet",
    "saham": "Saham",
    "crypto": "Crypto",
    "mutual_fund": "Mutual Fund",
    "reksadana": "Reksadana",
    "obligasi": "Obligasi",
    "deposito": "Deposito",
    "emas": "Emas",
    "properti": "Properti",
    "cash": "Cash",
    "other": "Other",
    "save_saving_space": "Save Saving Space",
    "edit_saving_space": "Edit Saving Space",
    "add_new_category": "Add New Category",
    "category_name": "Category Name",
    "category_name_required": "Category Name *",
    "enter_category_name": "Enter category name",
    "enter_category_description_optional": "Enter category description (optional)",
    "save_category": "Save Category",
    "edit_category": "Edit Category",
    "scope_created": "Scope created successfully!",
    "scope_updated": "Scope updated successfully!",
    "failed_save_scope": "Failed to save scope",
    "delete_scope_confirm": "Are you sure you want to delete this scope?",
    "scope_deleted": "Scope deleted successfully!",
    "failed_delete_scope": "Failed to delete scope",
    "saving_space_created": "Saving space created successfully!",
    "saving_space_updated": "Saving space updated successfully!",
    "failed_save_saving_space": "Failed to save saving space",
    "delete_saving_space_confirm": "Are you sure you want to delete this saving space?",
    "saving_space_deleted": "Saving space deleted successfully!",
    "failed_delete_saving_space": "Failed to delete saving space",
    "category_created": "Category created successfully!",
    "category_updated": "Category updated successfully!",
    "failed_save_category": "Failed to save category",
    "system_categories_cannot_edit": "System categories cannot be edited or deleted.",
    "delete_category_confirm": "Are you sure you want to delete this category?",
    "category_deleted": "Category deleted successfully!",
    "failed_delete_category": "Failed to delete category"
  },
  "ai_advisor": {
    "title": "AI Financial Advisor",
    "subtitle": "Get personalized financial insights and smart recommendations",
    "financial_ai_assistant": "Financial AI Assistant",
    "powered_by_ai": "Powered by advanced AI technology",
    "pro_badge": "PRO",
    "welcome_title": "Welcome to AI Financial Advisor!",
    "welcome_message": "I'm your intelligent financial companion, ready to help you make smarter money decisions.",
    "welcome_description": "Ask me about your spending patterns, budget optimization, investment strategies, or any financial questions you have!",
    "pro_tip": "Pro tip:",
    "pro_tip_description": "Type @ to see available helpers for categories, accounts, and scopes!",
    "ai_analyzing": "AI is analyzing your request",
    "ask_anything_placeholder": "Ask me anything about your finances... (type @ to see helpers)",
    "quick_helpers": "Quick Helpers",
    "type_at_description": "Type @ to see these options",
    "categories": "Categories",
    "accounts": "Accounts",
    "scopes": "Scopes",
    "clear_chat_confirm": "Are you sure you want to clear the chat history?",
    "error_saving_conversation": "Sorry, there was an error saving the conversation.",
    "ai_by": "AI by",
    "local": "Local"
  }
}
